focus_timer/__init__.py
focus_timer/banner_utils.py
focus_timer/cli.py
focus_timer/timer_utils.py
focus_timer_cli-0.1.0.dist-info/licenses/LICENSE
focus_timer_cli-0.1.0.dist-info/METADATA
focus_timer_cli-0.1.0.dist-info/WHEEL
focus_timer_cli-0.1.0.dist-info/entry_points.txt
focus_timer_cli-0.1.0.dist-info/top_level.txt
focus_timer_cli-0.1.0.dist-info/RECORD
