Metadata-Version: 2.4
Name: focus-timer-cli
Version: 0.1.0
Summary: A simple focus timer CLI to help you stay productive.
Author-email: Hariom Jha <jhahariom040@gmail.com>
Requires-Python: >=3.11
License-File: LICENSE
Requires-Dist: rich
Requires-Dist: typer
Requires-Dist: click
Dynamic: license-file
